crud_views/__init__.py
crud_views/apps.py
crud_views/checks.py
crud_views/lib/__init__.py
crud_views/lib/check.py
crud_views/lib/context_processor.py
crud_views/lib/exceptions.py
crud_views/lib/session.py
crud_views/lib/settings.py
crud_views/lib/crispy/__init__.py
crud_views/lib/crispy/form.py
crud_views/lib/crispy/table.py
crud_views/lib/formsets/__init__.py
crud_views/lib/formsets/formsets.py
crud_views/lib/formsets/inline_formset.py
crud_views/lib/formsets/layout.py
crud_views/lib/formsets/mixins.py
crud_views/lib/formsets/x.py
crud_views/lib/polymorphic_views/__init__.py
crud_views/lib/polymorphic_views/create.py
crud_views/lib/polymorphic_views/create_select.py
crud_views/lib/polymorphic_views/delete.py
crud_views/lib/polymorphic_views/detail.py
crud_views/lib/polymorphic_views/update.py
crud_views/lib/polymorphic_views/utils.py
crud_views/lib/table/__init__.py
crud_views/lib/table/attrs.py
crud_views/lib/table/columns.py
crud_views/lib/table/table.py
crud_views/lib/view/__init__.py
crud_views/lib/view/base.py
crud_views/lib/view/buttons.py
crud_views/lib/view/context.py
crud_views/lib/view/meta.py
crud_views/lib/view/property.py
crud_views/lib/views/__init__.py
crud_views/lib/views/action.py
crud_views/lib/views/action_ordered.py
crud_views/lib/views/child.py
crud_views/lib/views/create.py
crud_views/lib/views/delete.py
crud_views/lib/views/detail.py
crud_views/lib/views/form.py
crud_views/lib/views/list.py
crud_views/lib/views/manage.py
crud_views/lib/views/mixins.py
crud_views/lib/views/update.py
crud_views/lib/views/properties/__init__.py
crud_views/lib/views/properties/r.py
crud_views/lib/views/tabs/__init__.py
crud_views/lib/viewset/__init__.py
crud_views/lib/viewset/parentviewset.py
crud_views/lib/viewset/path_regs.py
crud_views/management/__init__.py
crud_views/management/commands/__init__.py
crud_views/management/commands/crud_views_show.py
crud_views/migrations/__init__.py
crud_views/static/crud_views/css/property.css
django_crud_views-0.0.10.dist-info/METADATA
django_crud_views-0.0.10.dist-info/WHEEL
django_crud_views-0.0.10.dist-info/licenses/LICENSE
django_crud_views-0.0.10.dist-info/RECORD
