Metadata-Version: 2.4
Name: django-crud-views
Version: 0.0.10
Summary: Django Crud Views
Project-URL: Homepage, https://github.com/jacob-consulting/django-crud-views
Project-URL: Documentation, https://django-crud-views.readthedocs.io/en/latest/
Project-URL: Repository, https://github.com:jacob-consulting/django-crud-views.git
Project-URL: Issues, https://github.com/jacob-consulting/django-crud-views/issues
Project-URL: Changelog, https://github.com/jacob-consulting/django-crud-views/blob/main/CHANGELOG.md
Author-email: Alexander Jacob <alexander.jacob@jacob-consulting.de>
License: MIT
License-File: LICENSE
Classifier: Development Status :: 3 - Alpha
Classifier: Framework :: Django
Classifier: Framework :: Django :: 4.2
Classifier: Framework :: Django :: 5
Classifier: Framework :: Django :: 5.2
Classifier: Intended Audience :: Developers
Classifier: Programming Language :: Python
Classifier: Programming Language :: Python :: 3.10
Classifier: Programming Language :: Python :: 3.11
Classifier: Programming Language :: Python :: 3.12
Requires-Python: >=3.10
Requires-Dist: django-filter>=21.1
Requires-Dist: django-ordered-model>=3.4.3
Requires-Dist: django-tables2>=2.5.3
Requires-Dist: django>=4.2.0
Requires-Dist: pydantic>=2.2.1
Requires-Dist: python-box>=6.0.2
Requires-Dist: typing-extensions>=4.7.1
Provides-Extra: bootstrap5
Requires-Dist: crispy-bootstrap5>=2023.10; extra == 'bootstrap5'
Requires-Dist: django-bootstrap5>=21.3; extra == 'bootstrap5'
Requires-Dist: django-crispy-forms>=2.0; extra == 'bootstrap5'
Provides-Extra: bootstrap5minimal
Requires-Dist: crispy-bootstrap5==2023.10; extra == 'bootstrap5minimal'
Requires-Dist: django-bootstrap5==21.3; extra == 'bootstrap5minimal'
Requires-Dist: django-crispy-forms==2.0; extra == 'bootstrap5minimal'
Provides-Extra: dev
Requires-Dist: black; extra == 'dev'
Requires-Dist: bumpver; extra == 'dev'
Requires-Dist: mkdocs-awesome-pages-plugin>=2.10.1; extra == 'dev'
Requires-Dist: mkdocs-get-deps>=0.2.0; extra == 'dev'
Requires-Dist: mkdocs>=1.6.1; extra == 'dev'
Provides-Extra: minimal
Requires-Dist: django-filter==21.1; extra == 'minimal'
Requires-Dist: django-ordered-model==3.4.3; extra == 'minimal'
Requires-Dist: django-tables2==2.5.3; extra == 'minimal'
Requires-Dist: django==4.2.0; extra == 'minimal'
Requires-Dist: pydantic==2.2.1; extra == 'minimal'
Requires-Dist: python-box==6.0.2; extra == 'minimal'
Requires-Dist: typing-extensions==4.7.1; extra == 'minimal'
Provides-Extra: polymorphic
Requires-Dist: django-polymorphic>=3.1.0; extra == 'polymorphic'
Requires-Dist: setuptools; extra == 'polymorphic'
Provides-Extra: test
Requires-Dist: lxml; extra == 'test'
Requires-Dist: nox; extra == 'test'
Requires-Dist: pytest; extra == 'test'
Requires-Dist: pytest-cov; extra == 'test'
Requires-Dist: pytest-django; extra == 'test'
Requires-Dist: pytest-mock; extra == 'test'
Requires-Dist: pytest-random-order; extra == 'test'
